LICENSE
MANIFEST.in
README.rst
setup.cfg
setup.py
gunicorn_logging/__init__.py
gunicorn_logging/apps.py
gunicorn_logging/formatters.py
gunicorn_logging/handlers.py
gunicorn_logging/settings.py
gunicorn_logging.egg-info/PKG-INFO
gunicorn_logging.egg-info/SOURCES.txt
gunicorn_logging.egg-info/dependency_links.txt
gunicorn_logging.egg-info/requires.txt
gunicorn_logging.egg-info/top_level.txt
gunicorn_logging/__pycache__/__init__.cpython-36.pyc
gunicorn_logging/__pycache__/apps.cpython-36.pyc
gunicorn_logging/__pycache__/formatters.cpython-36.pyc
gunicorn_logging/__pycache__/handlers.cpython-36.pyc
gunicorn_logging/__pycache__/settings.cpython-36.pyc