Metadata-Version: 2.1
Name: gunicorn-logging
Version: 0.1.0
Summary: Gunicorn centralized logging
Home-page: https://github.com/emilioag/gunicorn-logging/
Author: emilioag
Author-email: emilioag@mail.com
License: UNKNOWN
Keywords: django,logging,gunicorn,logstash,elk
Platform: UNKNOWN
Classifier: Development Status :: 3 - Alpha
Classifier: Intended Audience :: Developers
Classifier: Topic :: Software Development :: Documentation
Classifier: License :: OSI Approved :: MIT License
Classifier: Programming Language :: Python :: 3.6
Provides-Extra: test
Provides-Extra: dev
